{"id":"px368LdsbpQ","created_at":"2015-10-12T12:25:19-04:00","updated_at":"2017-08-25T03:46:24-04:00","width":6000,"height":4000,"color":"#7496B3","slug":null,"downloads":4635,"likes":79,"views":665987,"liked_by_user":false,"description":null,"exif":{"make":"Sony","model":"ILCE-6000","exposure_time":"1/4000","aperture":"4.5","focal_length":"16","iso":100},"location":{"title":"Ставангер, Stavanger, Norway","name":"Ставангер","city":"Stavanger","country":"Norway","position":{"latitude":58.9699756,"longitude":5.73310730000003}},"current_user_collections":[],"urls":{"raw":"https://images.unsplash.com/photo-1444666892507-8116378da2f4","full":"https://images.unsplash.com/photo-1444666892507-8116378da2f4?ixlib=rb-0.3.5&q=85&fm=jpg&crop=entropy&cs=srgb&s=1f1b1986c12fc286a962f55062d493a9","regular":"https://images.unsplash.com/photo-1444666892507-8116378da2f4?ixlib=rb-0.3.5&q=80&fm=jpg&crop=entropy&cs=tinysrgb&w=1080&fit=max&s=603c638046e2ba60535147b4536785ab","small":"https://images.unsplash.com/photo-1444666892507-8116378da2f4?ixlib=rb-0.3.5&q=80&fm=jpg&crop=entropy&cs=tinysrgb&w=400&fit=max&s=4dbc240b1ed66e2035b873cb15bbd92b","thumb":"https://images.unsplash.com/photo-1444666892507-8116378da2f4?ixlib=rb-0.3.5&q=80&fm=jpg&crop=entropy&cs=tinysrgb&w=200&fit=max&s=ffe9cf4cedd0d20faa0da241d4e8971c"},"categories":[{"id":4,"title":"Nature","photo_count":54184,"links":{"self":"https://api.unsplash.com/categories/4","photos":"https://api.unsplash.com/categories/4/photos"}}],"links":{"self":"https://api.unsplash.com/photos/px368LdsbpQ","html":"https://unsplash.com/photos/px368LdsbpQ","download":"https://unsplash.com/photos/px368LdsbpQ/download","download_location":"https://api.unsplash.com/photos/px368LdsbpQ/download"},"user":{"id":"Nki49rF3rvc","updated_at":"2017-08-26T01:10:04-04:00","username":"devilcoders","name":"Alexey Topolyanskiy","first_name":"Alexey","last_name":"Topolyanskiy","twitter_username":"devilcoders","portfolio_url":"http://alexify.me","bio":"I'm a designer, web developer, musician, traveler, and enthusiast photographer from Lviv, Ukraine. Currently, I'm living and working in Warsaw, Poland.","location":"Warsaw, Poland","total_likes":35,"total_photos":44,"total_collections":16,"profile_image":{"small":"https://images.unsplash.com/profile-1443992219960-87f028838fb9?ixlib=rb-0.3.5&q=80&fm=jpg&crop=faces&cs=tinysrgb&fit=crop&h=32&w=32&s=1cc3577fca2a428d3cef249c48a59a73","medium":"https://images.unsplash.com/profile-1443992219960-87f028838fb9?ixlib=rb-0.3.5&q=80&fm=jpg&crop=faces&cs=tinysrgb&fit=crop&h=64&w=64&s=d34838a78b045d515da2ef0b56fcaf5d","large":"https://images.unsplash.com/profile-1443992219960-87f028838fb9?ixlib=rb-0.3.5&q=80&fm=jpg&crop=faces&cs=tinysrgb&fit=crop&h=128&w=128&s=ffae99336758b84e0e1a32a17ca4b732"},"links":{"self":"https://api.unsplash.com/users/devilcoders","html":"https://unsplash.com/@devilcoders","photos":"https://api.unsplash.com/users/devilcoders/photos","likes":"https://api.unsplash.com/users/devilcoders/likes","portfolio":"https://api.unsplash.com/users/devilcoders/portfolio","following":"https://api.unsplash.com/users/devilcoders/following","followers":"https://api.unsplash.com/users/devilcoders/followers"}}}