{"id":"7oxd5HfTLiE","created_at":"2017-02-01T10:53:40-05:00","updated_at":"2017-09-13T01:57:38-04:00","width":6016,"height":4000,"color":"#8C7F79","slug":null,"downloads":0,"likes":36,"views":0,"liked_by_user":false,"description":null,"exif":{"make":"Nikon","model":"NIKON D3200","exposure_time":"30","aperture":"3.5","focal_length":"18","iso":3200},"location":{"title":"Pfelders im Passeiertal, Italy","name":"Pfelders im Passeiertal","city":null,"country":"Italy","position":{"latitude":46.7970748,"longitude":11.0919881}},"current_user_collections":[],"urls":{"raw":"https://images.unsplash.com/photo-1485964004367-e6fac77f8c86","full":"https://images.unsplash.com/photo-1485964004367-e6fac77f8c86?ixlib=rb-0.3.5&q=85&fm=jpg&crop=entropy&cs=srgb&s=0d70db9b1c654786f0bd3ecc9f7fa17e","regular":"https://images.unsplash.com/photo-1485964004367-e6fac77f8c86?ixlib=rb-0.3.5&q=80&fm=jpg&crop=entropy&cs=tinysrgb&w=1080&fit=max&s=04b05dde606ac304acee4f0c5f9b25d1","small":"https://images.unsplash.com/photo-1485964004367-e6fac77f8c86?ixlib=rb-0.3.5&q=80&fm=jpg&crop=entropy&cs=tinysrgb&w=400&fit=max&s=7042ffe8ae63cf3d67077e467f9df10e","thumb":"https://images.unsplash.com/photo-1485964004367-e6fac77f8c86?ixlib=rb-0.3.5&q=80&fm=jpg&crop=entropy&cs=tinysrgb&w=200&fit=max&s=a3cfc30d420a965b24c739ea20b2df8e"},"categories":[],"links":{"self":"https://api.unsplash.com/photos/7oxd5HfTLiE","html":"https://unsplash.com/photos/7oxd5HfTLiE","download":"https://unsplash.com/photos/7oxd5HfTLiE/download","download_location":"https://api.unsplash.com/photos/7oxd5HfTLiE/download"},"user":{"id":"yt1mOjS_OAA","updated_at":"2017-09-13T01:57:38-04:00","username":"lynn23","name":"Linda Schwarz","first_name":"Linda","last_name":"Schwarz","twitter_username":null,"portfolio_url":null,"bio":"","location":null,"total_likes":14,"total_photos":7,"total_collections":0,"profile_image":{"small":"https://images.unsplash.com/profile-fb-1484408035-a9f2f7c53d5e.jpg?ixlib=rb-0.3.5&q=80&fm=jpg&crop=faces&cs=tinysrgb&fit=crop&h=32&w=32&s=96f7ebf6d8c45f0918ff00f063556cf2","medium":"https://images.unsplash.com/profile-fb-1484408035-a9f2f7c53d5e.jpg?ixlib=rb-0.3.5&q=80&fm=jpg&crop=faces&cs=tinysrgb&fit=crop&h=64&w=64&s=26e279a3775fd3c1f233dd67a5440019","large":"https://images.unsplash.com/profile-fb-1484408035-a9f2f7c53d5e.jpg?ixlib=rb-0.3.5&q=80&fm=jpg&crop=faces&cs=tinysrgb&fit=crop&h=128&w=128&s=75a3610d3709cdb85eb11b2170107815"},"links":{"self":"https://api.unsplash.com/users/lynn23","html":"https://unsplash.com/@lynn23","photos":"https://api.unsplash.com/users/lynn23/photos","likes":"https://api.unsplash.com/users/lynn23/likes","portfolio":"https://api.unsplash.com/users/lynn23/portfolio","following":"https://api.unsplash.com/users/lynn23/following","followers":"https://api.unsplash.com/users/lynn23/followers"}}}