{"id":"NbBJeZbweKA","created_at":"2016-08-04T04:41:36-04:00","updated_at":"2017-08-17T14:34:56-04:00","width":4277,"height":2841,"color":"#ECECE8","slug":null,"downloads":3356,"likes":80,"views":291709,"liked_by_user":false,"description":null,"exif":{"make":"Nikon","model":"NIKON D90","exposure_time":"20","aperture":"6.3","focal_length":"28","iso":320},"current_user_collections":[],"urls":{"raw":"https://images.unsplash.com/photo-1470300087050-0b03a2e40462","full":"https://images.unsplash.com/photo-1470300087050-0b03a2e40462?ixlib=rb-0.3.5&q=85&fm=jpg&crop=entropy&cs=srgb&s=297ba5f631f4f3f151b73e15ff741210","regular":"https://images.unsplash.com/photo-1470300087050-0b03a2e40462?ixlib=rb-0.3.5&q=80&fm=jpg&crop=entropy&cs=tinysrgb&w=1080&fit=max&s=d9c468c9e2e113ea9663579231a3bd19","small":"https://images.unsplash.com/photo-1470300087050-0b03a2e40462?ixlib=rb-0.3.5&q=80&fm=jpg&crop=entropy&cs=tinysrgb&w=400&fit=max&s=bf343a73e4b47bf044c619be84ec9ca9","thumb":"https://images.unsplash.com/photo-1470300087050-0b03a2e40462?ixlib=rb-0.3.5&q=80&fm=jpg&crop=entropy&cs=tinysrgb&w=200&fit=max&s=a42dccb6b72cf63fed99a89235b351c2"},"categories":[{"id":4,"title":"Nature","photo_count":54184,"links":{"self":"https://api.unsplash.com/categories/4","photos":"https://api.unsplash.com/categories/4/photos"}}],"links":{"self":"https://api.unsplash.com/photos/NbBJeZbweKA","html":"https://unsplash.com/photos/NbBJeZbweKA","download":"https://unsplash.com/photos/NbBJeZbweKA/download","download_location":"https://api.unsplash.com/photos/NbBJeZbweKA/download"},"user":{"id":"T392i7U247c","updated_at":"2017-08-21T11:12:19-04:00","username":"sweetybeard","name":"Dmitry Ermakov","first_name":"Dmitry","last_name":"Ermakov","twitter_username":null,"portfolio_url":"https://vk.com/id12009977","bio":"","location":null,"total_likes":1,"total_photos":11,"total_collections":0,"profile_image":{"small":"https://images.unsplash.com/profile-1470299328034-9e7792c1f63a?ixlib=rb-0.3.5&q=80&fm=jpg&crop=faces&cs=tinysrgb&fit=crop&h=32&w=32&s=6fa15dc5d0f3bb25db196d4598229b87","medium":"https://images.unsplash.com/profile-1470299328034-9e7792c1f63a?ixlib=rb-0.3.5&q=80&fm=jpg&crop=faces&cs=tinysrgb&fit=crop&h=64&w=64&s=23f263b1792329bed047d52c77b364b8","large":"https://images.unsplash.com/profile-1470299328034-9e7792c1f63a?ixlib=rb-0.3.5&q=80&fm=jpg&crop=faces&cs=tinysrgb&fit=crop&h=128&w=128&s=74cbc8f7ca667fb07ca64f093b85fcd7"},"links":{"self":"https://api.unsplash.com/users/sweetybeard","html":"https://unsplash.com/@sweetybeard","photos":"https://api.unsplash.com/users/sweetybeard/photos","likes":"https://api.unsplash.com/users/sweetybeard/likes","portfolio":"https://api.unsplash.com/users/sweetybeard/portfolio","following":"https://api.unsplash.com/users/sweetybeard/following","followers":"https://api.unsplash.com/users/sweetybeard/followers"}}}