{"id":"-dsVRH3VfyY","created_at":"2015-10-07T05:54:22-04:00","updated_at":"2017-09-20T21:56:21-04:00","width":4000,"height":3000,"color":"#7D746D","slug":null,"downloads":3068,"likes":48,"views":1025613,"liked_by_user":false,"description":null,"exif":{"make":"Ricoh","model":"PENTAX 645Z","exposure_time":"1/4000","aperture":"5.0","focal_length":"55","iso":100},"location":{"title":"Liberty Island, New York, United States","name":"Liberty Island","city":"New York","country":"United States","position":{"latitude":40.6900495,"longitude":-74.0450675}},"current_user_collections":[],"urls":{"raw":"https://images.unsplash.com/photo-1444211589712-92bcd46c9ea9","full":"https://images.unsplash.com/photo-1444211589712-92bcd46c9ea9?ixlib=rb-0.3.5&q=85&fm=jpg&crop=entropy&cs=srgb&s=61f66e215005bc593500a81fa2598f71","regular":"https://images.unsplash.com/photo-1444211589712-92bcd46c9ea9?ixlib=rb-0.3.5&q=80&fm=jpg&crop=entropy&cs=tinysrgb&w=1080&fit=max&s=54d67e6e2155975ef63cb7890dcfdc7f","small":"https://images.unsplash.com/photo-1444211589712-92bcd46c9ea9?ixlib=rb-0.3.5&q=80&fm=jpg&crop=entropy&cs=tinysrgb&w=400&fit=max&s=b78019e83f9c2c561aac673904b50f02","thumb":"https://images.unsplash.com/photo-1444211589712-92bcd46c9ea9?ixlib=rb-0.3.5&q=80&fm=jpg&crop=entropy&cs=tinysrgb&w=200&fit=max&s=cad7ad8619ea55e81a249ecccd5338a9"},"categories":[],"links":{"self":"https://api.unsplash.com/photos/-dsVRH3VfyY","html":"https://unsplash.com/photos/-dsVRH3VfyY","download":"https://unsplash.com/photos/-dsVRH3VfyY/download","download_location":"https://api.unsplash.com/photos/-dsVRH3VfyY/download"},"user":{"id":"IFcEhJqem0Q","updated_at":"2017-09-20T22:10:14-04:00","username":"anniespratt","name":"Annie Spratt","first_name":"Annie","last_name":"Spratt","twitter_username":"anniespratt","portfolio_url":"http://mammasaurus.co.uk","bio":"Follow me , say hello and share how you use my photos at Twitter & Instagram @anniespratt ·\r\n         💌 annie@mammasaurus.co.uk\r\n","location":"New Forest National Park, UK","total_likes":12758,"total_photos":1041,"total_collections":48,"profile_image":{"small":"https://images.unsplash.com/profile-1489745565831-f4d9ecdf0195?ixlib=rb-0.3.5&q=80&fm=jpg&crop=faces&cs=tinysrgb&fit=crop&h=32&w=32&s=5d9873efe2c93573c4d1c957eaeddd43","medium":"https://images.unsplash.com/profile-1489745565831-f4d9ecdf0195?ixlib=rb-0.3.5&q=80&fm=jpg&crop=faces&cs=tinysrgb&fit=crop&h=64&w=64&s=64f6aca9a6ce63ef8113fe4883c2a7d2","large":"https://images.unsplash.com/profile-1489745565831-f4d9ecdf0195?ixlib=rb-0.3.5&q=80&fm=jpg&crop=faces&cs=tinysrgb&fit=crop&h=128&w=128&s=2f436cf179be351ec2ce55572739953c"},"links":{"self":"https://api.unsplash.com/users/anniespratt","html":"https://unsplash.com/@anniespratt","photos":"https://api.unsplash.com/users/anniespratt/photos","likes":"https://api.unsplash.com/users/anniespratt/likes","portfolio":"https://api.unsplash.com/users/anniespratt/portfolio","following":"https://api.unsplash.com/users/anniespratt/following","followers":"https://api.unsplash.com/users/anniespratt/followers"}}}