{"id":"fGZwklD-AEk","created_at":"2014-10-26T11:39:33-04:00","updated_at":"2017-07-29T08:14:40-04:00","width":4461,"height":2955,"color":"#B4B3B0","slug":null,"downloads":1732,"likes":13,"views":595124,"liked_by_user":false,"description":null,"exif":{"make":"Nikon","model":"NIKON D7000","exposure_time":"120/1","aperture":null,"focal_length":null,"iso":200},"current_user_collections":[],"urls":{"raw":"https://images.unsplash.com/photo-1414337969206-d37be66b227b","full":"https://images.unsplash.com/photo-1414337969206-d37be66b227b?ixlib=rb-0.3.5&q=85&fm=jpg&crop=entropy&cs=srgb&s=7a170323aafa1eada83b9fe4eb4989a4","regular":"https://images.unsplash.com/photo-1414337969206-d37be66b227b?ixlib=rb-0.3.5&q=80&fm=jpg&crop=entropy&cs=tinysrgb&w=1080&fit=max&s=9e1628de5fbc2dbc7c8d689ae132a5fb","small":"https://images.unsplash.com/photo-1414337969206-d37be66b227b?ixlib=rb-0.3.5&q=80&fm=jpg&crop=entropy&cs=tinysrgb&w=400&fit=max&s=63bc137d98acc8c271950d840ec5c70a","thumb":"https://images.unsplash.com/photo-1414337969206-d37be66b227b?ixlib=rb-0.3.5&q=80&fm=jpg&crop=entropy&cs=tinysrgb&w=200&fit=max&s=ff7dc6e9fc37d313038ba4caff417908"},"categories":[{"id":4,"title":"Nature","photo_count":54184,"links":{"self":"https://api.unsplash.com/categories/4","photos":"https://api.unsplash.com/categories/4/photos"}}],"links":{"self":"https://api.unsplash.com/photos/fGZwklD-AEk","html":"https://unsplash.com/photos/fGZwklD-AEk","download":"https://unsplash.com/photos/fGZwklD-AEk/download","download_location":"https://api.unsplash.com/photos/fGZwklD-AEk/download"},"user":{"id":"VqD0n8xd_2s","updated_at":"2017-08-22T04:10:05-04:00","username":"araltasher","name":"Aral Tasher","first_name":"Aral","last_name":"Tasher","twitter_username":"araltasher","portfolio_url":"http://www.araltasher.com","bio":"","location":null,"total_likes":37,"total_photos":67,"total_collections":1,"profile_image":{"small":"https://images.unsplash.com/profile-1444063949178-ba5550a5f335?ixlib=rb-0.3.5&q=80&fm=jpg&crop=faces&cs=tinysrgb&fit=crop&h=32&w=32&s=c66fcd397265916cc95890b9e381f5fb","medium":"https://images.unsplash.com/profile-1444063949178-ba5550a5f335?ixlib=rb-0.3.5&q=80&fm=jpg&crop=faces&cs=tinysrgb&fit=crop&h=64&w=64&s=3ddce869ec10247e0544f8b98954b622","large":"https://images.unsplash.com/profile-1444063949178-ba5550a5f335?ixlib=rb-0.3.5&q=80&fm=jpg&crop=faces&cs=tinysrgb&fit=crop&h=128&w=128&s=19348869a738a07fb085e77a20f86da9"},"links":{"self":"https://api.unsplash.com/users/araltasher","html":"https://unsplash.com/@araltasher","photos":"https://api.unsplash.com/users/araltasher/photos","likes":"https://api.unsplash.com/users/araltasher/likes","portfolio":"https://api.unsplash.com/users/araltasher/portfolio","following":"https://api.unsplash.com/users/araltasher/following","followers":"https://api.unsplash.com/users/araltasher/followers"}}}