{"id":"TeX_yWATaBA","created_at":"2015-01-01T13:19:56-05:00","updated_at":"2017-09-15T02:14:20-04:00","width":4836,"height":3203,"color":"#887E86","slug":null,"downloads":0,"likes":118,"views":1186917,"liked_by_user":false,"description":"Evening horizon featuring the reflection of the sunset on the sea at dawn","exif":{"make":"Nikon","model":"NIKON D5100","exposure_time":"1/200","aperture":"4.5","focal_length":"17","iso":125},"current_user_collections":[],"urls":{"raw":"https://images.unsplash.com/photo-1420136390439-1482fc2ce4b9","full":"https://images.unsplash.com/photo-1420136390439-1482fc2ce4b9?ixlib=rb-0.3.5&q=85&fm=jpg&crop=entropy&cs=srgb&s=185f7a4a8b1b2ffb8bc464658d6575a4","regular":"https://images.unsplash.com/photo-1420136390439-1482fc2ce4b9?ixlib=rb-0.3.5&q=80&fm=jpg&crop=entropy&cs=tinysrgb&w=1080&fit=max&s=8cfa948a3a3cd517ad3777ed51567c4e","small":"https://images.unsplash.com/photo-1420136390439-1482fc2ce4b9?ixlib=rb-0.3.5&q=80&fm=jpg&crop=entropy&cs=tinysrgb&w=400&fit=max&s=0e75a9320eab3525c3f7e084e75d48e3","thumb":"https://images.unsplash.com/photo-1420136390439-1482fc2ce4b9?ixlib=rb-0.3.5&q=80&fm=jpg&crop=entropy&cs=tinysrgb&w=200&fit=max&s=dc2ad833d2765cdf8895e4b77ac81613"},"categories":[],"links":{"self":"https://api.unsplash.com/photos/TeX_yWATaBA","html":"https://unsplash.com/photos/TeX_yWATaBA","download":"https://unsplash.com/photos/TeX_yWATaBA/download","download_location":"https://api.unsplash.com/photos/TeX_yWATaBA/download"},"user":{"id":"dyep3Lxrna0","updated_at":"2017-09-18T14:50:17-04:00","username":"hideobara","name":"Hide Obara","first_name":"Hide","last_name":"Obara","twitter_username":null,"portfolio_url":"http://www.hideobara.com","bio":"","location":null,"total_likes":0,"total_photos":19,"total_collections":0,"profile_image":{"small":"https://images.unsplash.com/profile-1498666612429-4cd3d484fa55?ixlib=rb-0.3.5&q=80&fm=jpg&crop=faces&cs=tinysrgb&fit=crop&h=32&w=32&s=83cd8936a183aee86791031563f68878","medium":"https://images.unsplash.com/profile-1498666612429-4cd3d484fa55?ixlib=rb-0.3.5&q=80&fm=jpg&crop=faces&cs=tinysrgb&fit=crop&h=64&w=64&s=1eb1670f49590d991ce9141d111f7cde","large":"https://images.unsplash.com/profile-1498666612429-4cd3d484fa55?ixlib=rb-0.3.5&q=80&fm=jpg&crop=faces&cs=tinysrgb&fit=crop&h=128&w=128&s=4beb6fc2080475d9c9a6391ff40340ac"},"links":{"self":"https://api.unsplash.com/users/hideobara","html":"https://unsplash.com/@hideobara","photos":"https://api.unsplash.com/users/hideobara/photos","likes":"https://api.unsplash.com/users/hideobara/likes","portfolio":"https://api.unsplash.com/users/hideobara/portfolio","following":"https://api.unsplash.com/users/hideobara/following","followers":"https://api.unsplash.com/users/hideobara/followers"}}}