{"id":"HNS9TwcIfzQ","created_at":"2016-08-31T05:09:45-04:00","updated_at":"2017-09-15T03:08:43-04:00","width":3992,"height":2242,"color":"#2E3331","slug":null,"downloads":0,"likes":804,"views":0,"liked_by_user":false,"description":null,"exif":{"make":"DJI","model":"FC300S","exposure_time":"1/4000","aperture":"2.8","focal_length":"3.6","iso":100},"location":{"title":"Durdle Door, Wareham, United Kingdom","name":"Durdle Door","city":"Wareham","country":"United Kingdom","position":{"latitude":50.621149,"longitude":-2.27545750000002}},"current_user_collections":[],"urls":{"raw":"https://images.unsplash.com/photo-1472634511615-7ce0fcc2c100","full":"https://images.unsplash.com/photo-1472634511615-7ce0fcc2c100?ixlib=rb-0.3.5&q=85&fm=jpg&crop=entropy&cs=srgb&s=47bdf6a1faf9e14c2840e3115d41fd87","regular":"https://images.unsplash.com/photo-1472634511615-7ce0fcc2c100?ixlib=rb-0.3.5&q=80&fm=jpg&crop=entropy&cs=tinysrgb&w=1080&fit=max&s=73aaa967e59183cf6fc71cd111d0ecbc","small":"https://images.unsplash.com/photo-1472634511615-7ce0fcc2c100?ixlib=rb-0.3.5&q=80&fm=jpg&crop=entropy&cs=tinysrgb&w=400&fit=max&s=3618c35ac83b078151d3e79372376e14","thumb":"https://images.unsplash.com/photo-1472634511615-7ce0fcc2c100?ixlib=rb-0.3.5&q=80&fm=jpg&crop=entropy&cs=tinysrgb&w=200&fit=max&s=3314102c10ee221c82a71167d4dcf418"},"categories":[],"links":{"self":"https://api.unsplash.com/photos/HNS9TwcIfzQ","html":"https://unsplash.com/photos/HNS9TwcIfzQ","download":"https://unsplash.com/photos/HNS9TwcIfzQ/download","download_location":"https://api.unsplash.com/photos/HNS9TwcIfzQ/download"},"user":{"id":"UAanJIX4Xpc","updated_at":"2017-09-18T05:16:59-04:00","username":"sidharthbhatia","name":"Sidharth Bhatia","first_name":"Sidharth","last_name":"Bhatia","twitter_username":null,"portfolio_url":null,"bio":"","location":null,"total_likes":8,"total_photos":13,"total_collections":0,"profile_image":{"small":"https://images.unsplash.com/profile-fb-1471375935-c1f38264936c.jpg?ixlib=rb-0.3.5&q=80&fm=jpg&crop=faces&cs=tinysrgb&fit=crop&h=32&w=32&s=b3da649df9447f1848a0af59addff47c","medium":"https://images.unsplash.com/profile-fb-1471375935-c1f38264936c.jpg?ixlib=rb-0.3.5&q=80&fm=jpg&crop=faces&cs=tinysrgb&fit=crop&h=64&w=64&s=31aee82e96c0cdd48bf720f7b49a8ded","large":"https://images.unsplash.com/profile-fb-1471375935-c1f38264936c.jpg?ixlib=rb-0.3.5&q=80&fm=jpg&crop=faces&cs=tinysrgb&fit=crop&h=128&w=128&s=39a16a013337d392df4b5a9aad3ebd12"},"links":{"self":"https://api.unsplash.com/users/sidharthbhatia","html":"https://unsplash.com/@sidharthbhatia","photos":"https://api.unsplash.com/users/sidharthbhatia/photos","likes":"https://api.unsplash.com/users/sidharthbhatia/likes","portfolio":"https://api.unsplash.com/users/sidharthbhatia/portfolio","following":"https://api.unsplash.com/users/sidharthbhatia/following","followers":"https://api.unsplash.com/users/sidharthbhatia/followers"}}}