{"id":"xB8FqHWsgTs","created_at":"2017-01-04T06:58:15-05:00","updated_at":"2017-08-28T01:52:44-04:00","width":4642,"height":3520,"color":"#E4D6BF","slug":null,"downloads":0,"likes":31,"views":0,"liked_by_user":false,"description":null,"exif":{"make":"Nikon","model":"NIKON D3300","exposure_time":"1/4000","aperture":"6.3","focal_length":"55","iso":200},"location":{"title":"Antwerp, Belgium","name":"Antwerp","city":"Antwerp","country":"Belgium","position":{"latitude":51.2005203970795,"longitude":4.41276398261721}},"current_user_collections":[],"urls":{"raw":"https://images.unsplash.com/photo-1483530922770-dde07d2f1871","full":"https://images.unsplash.com/photo-1483530922770-dde07d2f1871?ixlib=rb-0.3.5&q=85&fm=jpg&crop=entropy&cs=srgb&s=0be7437b595b4170960d1e8235a53ce0","regular":"https://images.unsplash.com/photo-1483530922770-dde07d2f1871?ixlib=rb-0.3.5&q=80&fm=jpg&crop=entropy&cs=tinysrgb&w=1080&fit=max&s=27477276aff1de2aecf39245fd0b8c26","small":"https://images.unsplash.com/photo-1483530922770-dde07d2f1871?ixlib=rb-0.3.5&q=80&fm=jpg&crop=entropy&cs=tinysrgb&w=400&fit=max&s=d5f59393e1a68aa8f1f86d5697f6db4d","thumb":"https://images.unsplash.com/photo-1483530922770-dde07d2f1871?ixlib=rb-0.3.5&q=80&fm=jpg&crop=entropy&cs=tinysrgb&w=200&fit=max&s=4089fc75c17d0edf4e39b615d83031c9"},"categories":[],"links":{"self":"https://api.unsplash.com/photos/xB8FqHWsgTs","html":"https://unsplash.com/photos/xB8FqHWsgTs","download":"https://unsplash.com/photos/xB8FqHWsgTs/download","download_location":"https://api.unsplash.com/photos/xB8FqHWsgTs/download"},"user":{"id":"ZPPvIUKoNgY","updated_at":"2017-09-17T13:40:00-04:00","username":"cedric","name":"Cédric Dhaenens","first_name":"Cédric","last_name":"Dhaenens","twitter_username":"CedricDhaenens","portfolio_url":"http://www.instagram.com/cedricdhaenens","bio":"Pilot. Photographer.","location":"Ghent, Belgium","total_likes":5,"total_photos":18,"total_collections":1,"profile_image":{"small":"https://images.unsplash.com/profile-1482492642838-54e3e86f870b?ixlib=rb-0.3.5&q=80&fm=jpg&crop=faces&cs=tinysrgb&fit=crop&h=32&w=32&s=36b69433945b5d1b0f7321d0153dea82","medium":"https://images.unsplash.com/profile-1482492642838-54e3e86f870b?ixlib=rb-0.3.5&q=80&fm=jpg&crop=faces&cs=tinysrgb&fit=crop&h=64&w=64&s=130ca019e348bdc83cbc7dcfebacf47f","large":"https://images.unsplash.com/profile-1482492642838-54e3e86f870b?ixlib=rb-0.3.5&q=80&fm=jpg&crop=faces&cs=tinysrgb&fit=crop&h=128&w=128&s=3650a06da30f065711c2df403bf9f187"},"links":{"self":"https://api.unsplash.com/users/cedric","html":"https://unsplash.com/@cedric","photos":"https://api.unsplash.com/users/cedric/photos","likes":"https://api.unsplash.com/users/cedric/likes","portfolio":"https://api.unsplash.com/users/cedric/portfolio","following":"https://api.unsplash.com/users/cedric/following","followers":"https://api.unsplash.com/users/cedric/followers"}}}