{"id":"9LghzF9GWg4","created_at":"2017-07-13T02:57:03-04:00","updated_at":"2017-09-10T14:00:37-04:00","width":4096,"height":2717,"color":"#0D0D0E","slug":null,"downloads":0,"likes":0,"views":0,"liked_by_user":false,"description":null,"exif":{"make":"Canon","model":"Canon EOS 7D","exposure_time":"1/4000","aperture":"2.8","focal_length":"19","iso":100},"location":{"title":"Lake Tekapo, New Zealand","name":"Lake Tekapo","city":"Lake Tekapo","country":"New Zealand","position":{"latitude":-44.0046736,"longitude":170.4771212}},"current_user_collections":[],"urls":{"raw":"https://images.unsplash.com/photo-1499928929153-62f4bdec5c8c","full":"https://images.unsplash.com/photo-1499928929153-62f4bdec5c8c?ixlib=rb-0.3.5&q=85&fm=jpg&crop=entropy&cs=srgb&s=d5ec1eaa023c96a777d921ca7fb4f601","regular":"https://images.unsplash.com/photo-1499928929153-62f4bdec5c8c?ixlib=rb-0.3.5&q=80&fm=jpg&crop=entropy&cs=tinysrgb&w=1080&fit=max&s=82d64d9f8b61c1d915d563acc931f2fb","small":"https://images.unsplash.com/photo-1499928929153-62f4bdec5c8c?ixlib=rb-0.3.5&q=80&fm=jpg&crop=entropy&cs=tinysrgb&w=400&fit=max&s=cb0646c3bbb6388955db47ca8f00ebe2","thumb":"https://images.unsplash.com/photo-1499928929153-62f4bdec5c8c?ixlib=rb-0.3.5&q=80&fm=jpg&crop=entropy&cs=tinysrgb&w=200&fit=max&s=97ad2d87f1fc0f30f56ec9e0cb9d2c80"},"categories":[],"links":{"self":"https://api.unsplash.com/photos/9LghzF9GWg4","html":"https://unsplash.com/photos/9LghzF9GWg4","download":"https://unsplash.com/photos/9LghzF9GWg4/download","download_location":"https://api.unsplash.com/photos/9LghzF9GWg4/download"},"user":{"id":"r48ilu9hOPY","updated_at":"2017-09-15T06:56:31-04:00","username":"janayadasiuk","name":"Janaya Dasiuk","first_name":"Janaya","last_name":"Dasiuk","twitter_username":null,"portfolio_url":null,"bio":"","location":null,"total_likes":0,"total_photos":18,"total_collections":0,"profile_image":{"small":"https://images.unsplash.com/profile-fb-1467195481-8e80477e075a.jpg?ixlib=rb-0.3.5&q=80&fm=jpg&crop=faces&cs=tinysrgb&fit=crop&h=32&w=32&s=82862afd1235c5a33b1ddd1b9a34d83f","medium":"https://images.unsplash.com/profile-fb-1467195481-8e80477e075a.jpg?ixlib=rb-0.3.5&q=80&fm=jpg&crop=faces&cs=tinysrgb&fit=crop&h=64&w=64&s=1fd8fef53501fe035ca1b48bc7dfe0af","large":"https://images.unsplash.com/profile-fb-1467195481-8e80477e075a.jpg?ixlib=rb-0.3.5&q=80&fm=jpg&crop=faces&cs=tinysrgb&fit=crop&h=128&w=128&s=35728b7f4ddd0b2fef90c8b731e1f445"},"links":{"self":"https://api.unsplash.com/users/janayadasiuk","html":"https://unsplash.com/@janayadasiuk","photos":"https://api.unsplash.com/users/janayadasiuk/photos","likes":"https://api.unsplash.com/users/janayadasiuk/likes","portfolio":"https://api.unsplash.com/users/janayadasiuk/portfolio","following":"https://api.unsplash.com/users/janayadasiuk/following","followers":"https://api.unsplash.com/users/janayadasiuk/followers"}}}